{
	"backtrace" : 0,
	"backtraceGraph" : 
	{
		"commands" : [],
		"files" : 
		[
			"QGobangServer/CMakeLists.txt"
		],
		"nodes" : 
		[
			{
				"file" : 0
			}
		]
	},
	"dependencies" : 
	[
		{
			"id" : "QGobangServer_autogen_timestamp_deps::@524db3ad240deb30a910"
		}
	],
	"folder" : 
	{
		"name" : "QtInternalTargets"
	},
	"id" : "QGobangServer_autogen::@524db3ad240deb30a910",
	"isGeneratorProvided" : true,
	"name" : "QGobangServer_autogen",
	"paths" : 
	{
		"build" : "QGobangServer",
		"source" : "QGobangServer"
	},
	"sourceGroups" : 
	[
		{
			"name" : "",
			"sourceIndexes" : 
			[
				0
			]
		},
		{
			"name" : "CMake Rules",
			"sourceIndexes" : 
			[
				1,
				2
			]
		}
	],
	"sources" : 
	[
		{
			"backtrace" : 0,
			"isGenerated" : true,
			"path" : "build/QGobangServer/CMakeFiles/QGobangServer_autogen",
			"sourceGroupIndex" : 0
		},
		{
			"backtrace" : 0,
			"isGenerated" : true,
			"path" : "build/QGobangServer/CMakeFiles/QGobangServer_autogen.rule",
			"sourceGroupIndex" : 1
		},
		{
			"backtrace" : 0,
			"isGenerated" : true,
			"path" : "build/QGobangServer/QGobangServer_autogen/timestamp.rule",
			"sourceGroupIndex" : 1
		}
	],
	"type" : "UTILITY"
}
